django_ninja_simple_jwt-0.7.1.dist-info/licenses/LICENSE
ninja_simple_jwt/__init__.py
ninja_simple_jwt/admin.py
ninja_simple_jwt/apps.py
ninja_simple_jwt/settings.py
ninja_simple_jwt/utils.py
ninja_simple_jwt/auth/__init__.py
ninja_simple_jwt/auth/ninja_auth.py
ninja_simple_jwt/auth/token_user.py
ninja_simple_jwt/auth/views/__init__.py
ninja_simple_jwt/auth/views/api.py
ninja_simple_jwt/auth/views/schemas.py
ninja_simple_jwt/jwt/__init__.py
ninja_simple_jwt/jwt/json_encode.py
ninja_simple_jwt/jwt/key_creation.py
ninja_simple_jwt/jwt/key_retrieval.py
ninja_simple_jwt/jwt/key_store.py
ninja_simple_jwt/jwt/token_operations.py
ninja_simple_jwt/management/__init__.py
ninja_simple_jwt/management/commands/__init__.py
ninja_simple_jwt/management/commands/make_rsa.py
tests/test_auth/__init__.py
tests/test_auth/test_api.py
tests/test_auth/test_ninja_auth.py
tests/test_auth/test_utils.py
tests/test_jwt/__init__.py
tests/test_jwt/test_json_encode.py
tests/test_jwt/test_token_operations.py
django_ninja_simple_jwt-0.7.1.dist-info/METADATA
django_ninja_simple_jwt-0.7.1.dist-info/WHEEL
django_ninja_simple_jwt-0.7.1.dist-info/top_level.txt
django_ninja_simple_jwt-0.7.1.dist-info/RECORD
