Metadata-Version: 2.4
Name: django-ninja-simple-jwt
Version: 0.7.1
Summary: Simple JWT-based authentication using Django and Django-ninja
Home-page: https://github.com/oscarychen/django-ninja-simple-jwt
Author: Oscar Chen
Author-email: quacky@duck.com
License: MIT
Classifier: Environment :: Web Environment
Classifier: Framework :: Django
Classifier: Framework :: Django :: 4.0
Classifier: Framework :: Django :: 4.1
Classifier: Framework :: Django :: 4.2
Classifier: Framework :: Django :: 5.0
Classifier: Framework :: Django :: 5.1
Classifier: Intended Audience :: Developers
Classifier: License :: OSI Approved :: BSD License
Classifier: Operating System :: OS Independent
Classifier: Programming Language :: Python
Classifier: Programming Language :: Python :: 3
Classifier: Programming Language :: Python :: 3.10
Classifier: Programming Language :: Python :: 3.11
Classifier: Programming Language :: Python :: 3.12
Classifier: Topic :: Internet :: WWW/HTTP
Classifier: Topic :: Internet :: WWW/HTTP :: Dynamic Content
Requires-Python: >=3.10
License-File: LICENSE
Requires-Dist: cryptography>=44.0.1
Requires-Dist: Django>=4.0
Requires-Dist: django-ninja>=1.0
Requires-Dist: pyjwt>=2.6
Dynamic: description-content-type
Dynamic: license-file
